[
    {
        "title": "Сок охлажденный J7 Апельсин с мякотью, 850мл",
        "sale_percent": 18,
        "card_price": 129.99,
        "regular_price": 157.89,
        "sale_start": "2022-07-25 02:00:00",
        "sale_end": "2022-09-07 02:00:00",
        "url": "https://lenta.com/product/sok-ohlazhdennyjj-j7-apelsin-rossiya-850ml-516159/"
    },
    {
        "title": "Нектар RICH Вишневый, 1л",
        "sale_percent": 48,
        "card_price": 119.89,
        "regular_price": 228.49,
        "sale_start": "2022-07-24 02:00:00",
        "sale_end": "2022-08-04 02:00:00",
        "url": "https://lenta.com/product/nektar-rich-vishnevyjj-tpak-rossiya-1l-102805/"
    },
    {
        "title": "Нектар RICH из апельсина и манго, 1л",
        "sale_percent": 48,
        "card_price": 119.89,
        "regular_price": 228.49,
        "sale_start": "2022-07-24 02:00:00",
        "sale_end": "2022-08-04 02:00:00",
        "url": "https://lenta.com/product/nektar-rich-iz-apelsina-i-mango-tpak-rossiya-1l-340735/"
    },
    {
        "title": "Сок RICH Мультифрукт, 1л",
        "sale_percent": 48,
        "card_price": 119.89,
        "regular_price": 228.49,
        "sale_start": "2022-07-24 02:00:00",
        "sale_end": "2022-08-04 02:00:00",
        "url": "https://lenta.com/product/sok-rich-multifrukt-sk-tpak-rossiya-1l-555471/"
    },
    {
        "title": "Сок охлажденный J7 Яблоко осветленный, 850мл",
        "sale_percent": 18,
        "card_price": 129.99,
        "regular_price": 157.89,
        "sale_start": "2022-07-25 02:00:00",
        "sale_end": "2022-09-07 02:00:00",
        "url": "https://lenta.com/product/sok-ohlazhdennyjj-j7-yabloko-rossiya-850ml-516016/"
    },
    {
        "title": "Сок J7 Fresh Taste из яблок, черники, аронии и ежевики с мякотью, 850мл",
        "sale_percent": 18,
        "card_price": 129.99,
        "regular_price": 157.89,
        "sale_start": "2022-07-25 02:00:00",
        "sale_end": "2022-09-07 02:00:00",
        "url": "https://lenta.com/product/sok-ohlazhdennyjj-j7-iz-yablok-cherniki-aronii-i-ezheviki-s-myakotyu-rossiya-850ml-577595/"
    },
    {
        "title": "Сок охлажденный J7 Whole Fruits Яблоко, персик с мякотью, 850мл",
        "sale_percent": 18,
        "card_price": 129.99,
        "regular_price": 157.89,
        "sale_start": "2022-07-25 02:00:00",
        "sale_end": "2022-09-07 02:00:00",
        "url": "https://lenta.com/product/sok-ohlazhdennyjj-j7-whole-fruits-yabloko-persik-rossiya-850ml-516017/"
    },
    {
        "title": "Сок BONVIDA Яблочный, 2л",
        "sale_percent": 11,
        "card_price": 159.99,
        "regular_price": 178.99,
        "sale_start": "2022-07-27 02:00:00",
        "sale_end": "2022-08-05 02:00:00",
        "url": "https://lenta.com/product/sok-prochie-tovary-yablochnyjj-tpak-rossiya-2l-612379/"
    },
    {
        "title": "Морс ФРУКТОВЫЙ САД Клюква, 0.95л",
        "sale_percent": 30,
        "card_price": 73.79,
        "regular_price": 105.29,
        "sale_start": "2022-07-27 02:00:00",
        "sale_end": "2022-08-24 02:00:00",
        "url": "https://lenta.com/product/mors-fruktovyjj-sad-klyukvennyjj-ddp-tpak-rossiya-095l-384692/"
    },
    {
        "title": "Квас БРОДИЧ Окрошечный нефильтрованный неосветленный, 1500мл",
        "sale_percent": 15,
        "card_price": 93.39,
        "regular_price": 109.99,
        "sale_start": "2022-07-24 02:00:00",
        "sale_end": "2022-11-01 02:00:00",
        "url": "https://lenta.com/product/kvas-brodich-okroshechnyjj-nefiltr-neosvet-pet-rossiya-1500ml-582753/"
    },
    {
        "title": "Сок ЛЕНТА Гранатовый прямого отжима, 0.31л",
        "sale_percent": 28,
        "card_price": 60.99,
        "regular_price": 84.29,
        "sale_start": "2022-07-27 02:00:00",
        "sale_end": "2022-08-10 02:00:00",
        "url": "https://lenta.com/product/sok-lenta-granatovyjj-pryamogo-otzhima-st-rossiya-031l-452942/"
    },
    {
        "title": "Сок ПЕРСОНА гранатовый восстановленный, 1л",
        "sale_percent": 17,
        "card_price": 72.69,
        "regular_price": 87.19,
        "sale_start": "2022-07-24 02:00:00",
        "sale_end": "2022-08-05 02:00:00",
        "url": "https://lenta.com/product/sok-persona-granatovyjj-vosst-st-rossiya-10l-562749/"
    },
    {
        "title": "Квас БРОДИЧ Домашний нефильтрованный неосветленный, 1500мл",
        "sale_percent": 45,
        "card_price": 59.99,
        "regular_price": 109.99,
        "sale_start": "2022-07-24 02:00:00",
        "sale_end": "2022-08-13 00:00:00",
        "url": "https://lenta.com/product/kvas-brodich-domashnijj-nefiltr-neosvetl-pet-rossiya-1500ml-582813/"
    },
    {
        "title": "Продукт питьевой J7 из яблок, персиков и манго с овсяными хлопьями, \r\n300мл",
        "sale_percent": 19,
        "card_price": 59.99,
        "regular_price": 73.69,
        "sale_start": "2022-07-24 02:00:00",
        "sale_end": "2022-08-01 02:00:00",
        "url": "https://lenta.com/product/produkt-pitevojj-j7-iz-yablok-persikov-i-mango-s-ovsyan-hlopyami-pet-rossiya-300ml-479833/"
    },
    {
        "title": "Сок охлажденный J7 Whole Fruits Мультифрукт с мякотью, 850мл",
        "sale_percent": 18,
        "card_price": 129.99,
        "regular_price": 157.89,
        "sale_start": "2022-07-25 02:00:00",
        "sale_end": "2022-09-07 02:00:00",
        "url": "https://lenta.com/product/sok-ohlazhdennyjj-j7-whole-fruits-multifrukt-rossiya-850ml-516160/"
    },
    {
        "title": "Морс ЛЕНТА PREMIUM Клюквенно-облепиховый, 1л",
        "sale_percent": 18,
        "card_price": 189.99,
        "regular_price": 231.59,
        "sale_start": "2022-07-29 02:00:00",
        "sale_end": "2022-08-04 00:00:00",
        "url": "https://lenta.com/product/mors-lenta-premium-klyukvenno-oblepihovyjj-st-rossiya-1l-603518/"
    },
    {
        "title": "Сок ДОБРЫЙ Active kid Супер Джус Яблоко, груша, 0.2л",
        "sale_percent": 32,
        "card_price": 28.89,
        "regular_price": 42.19,
        "sale_start": "2022-07-25 02:00:00",
        "sale_end": "2022-09-07 02:00:00",
        "url": "https://lenta.com/product/sok-dobryjj-super-dzhus-yabloko-grusha-active-kid-tpak-rossiya-02l-586624/"
    },
    {
        "title": "Сок ЛЕНТА Гранат и черная смородина восстановленный, 1л",
        "sale_percent": 22,
        "card_price": 139.99,
        "regular_price": 178.99,
        "sale_start": "2022-07-27 02:00:00",
        "sale_end": "2022-08-10 02:00:00",
        "url": "https://lenta.com/product/sok-lenta-granatovo-chernosmorodinovyjj-vosstanovlennyjj-st-rossiya-1l-554311/"
    },
    {
        "title": "Напиток сокосодержащий МОЯ СЕМЬЯ Ягода-Сочнягода, 0.175л",
        "sale_percent": 19,
        "card_price": 22.94,
        "regular_price": 28.49,
        "sale_start": "2022-07-24 02:00:00",
        "sale_end": "2022-08-04 02:00:00",
        "url": "https://lenta.com/product/napitok-sokosoderzhashchijj-moya-semya-yagoda-sochnyagoda-tpak-rossiya-0175l-573533/"
    },
    {
        "title": "Сок охлажденный J7 Апельсиновый с мякотью, 300мл",
        "sale_percent": 20,
        "card_price": 54.99,
        "regular_price": 68.49,
        "sale_start": "2022-07-25 02:00:00",
        "sale_end": "2022-09-07 02:00:00",
        "url": "https://lenta.com/product/sok-ohlazhdennyjj-j7-apelsinovyjj-s-myakotyu-rossiya-300ml-584409/"
    },
    {
        "title": "Квас МОНАСТЫРСКИЙ ДВОР Домашний, 1500мл",
        "sale_percent": 15,
        "card_price": 106.39,
        "regular_price": 125.29,
        "sale_start": "2022-07-24 02:00:00",
        "sale_end": "2022-11-01 02:00:00",
        "url": "https://lenta.com/product/kvas-monastyrskijj-dvor-domashnijj-pb-bez-zmzh-rossiya-1500ml-582633/"
    },
    {
        "title": "Нектар Любимый Солнечный нектарин с мякотью, 1.93л",
        "sale_percent": 30,
        "card_price": 125.29,
        "regular_price": 178.99,
        "sale_start": "2022-07-27 02:00:00",
        "sale_end": "2022-08-24 02:00:00",
        "url": "https://lenta.com/product/nektar-lyubimyjj-iz-yablok-persikov-i-nektarinov-s-myak-ddp-tpak-rossiya-193l-386523/"
    },
    {
        "title": "Сок ЛЕНТА Гранат и вишня восстановленный, 1л",
        "sale_percent": 22,
        "card_price": 139.99,
        "regular_price": 178.99,
        "sale_start": "2022-07-27 02:00:00",
        "sale_end": "2022-08-10 02:00:00",
        "url": "https://lenta.com/product/sok-lenta-granatovo-vishnevyjj-vosstanovlennyjj-st-rossiya-1l-554179/"
    },
    {
        "title": "Сок SWELL Апельсиновый с мякотью восстановленный, 0.75л",
        "sale_percent": 31,
        "card_price": 119.9,
        "regular_price": 173.39,
        "sale_start": "2022-07-27 02:00:00",
        "sale_end": "2022-08-05 00:00:00",
        "url": "https://lenta.com/product/sok-swell-apelsinovyjj-vosst-s-myak-st-rossiya-075l-180994/"
    }
]