[
    {
        "title": "Форель холодного копчения, балык, весовая",
        "sale_percent": 15,
        "card_price": 1789.39,
        "regular_price": 2105.29,
        "sale_start": "2022-07-24 02:00:00",
        "sale_end": "2022-11-04 02:00:00",
        "url": "https://lenta.com/product/forel-balyk-hk-ves-rossiya-1kg-104654/"
    },
    {
        "title": "Сельдь слабосоленая крупная 400г+, весовая",
        "sale_percent": 15,
        "card_price": 232.59,
        "regular_price": 273.69,
        "sale_start": "2022-07-24 02:00:00",
        "sale_end": "2022-11-04 02:00:00",
        "url": "https://lenta.com/product/seld-krupnaya-400-ss-ves-rossiya-1kg-504039/"
    },
    {
        "title": "Масляная рыба холодного копчения, филе, весовая",
        "sale_percent": 15,
        "card_price": 1395.79,
        "regular_price": 1642.19,
        "sale_start": "2022-07-24 02:00:00",
        "sale_end": "2022-11-04 02:00:00",
        "url": "https://lenta.com/product/maslyanaya-ryba-file-hk-ves-rossiya-143886/"
    },
    {
        "title": "Кета холодного копчения, филе, весовая",
        "sale_percent": 15,
        "card_price": 1055.79,
        "regular_price": 1242.19,
        "sale_start": "2022-07-24 02:00:00",
        "sale_end": "2022-11-04 02:00:00",
        "url": "https://lenta.com/product/keta-file-hk-ves-rossiya-443654/"
    },
    {
        "title": "Кальмар солено-сушеный, кольца, весовой",
        "sale_percent": 18,
        "card_price": 1299.99,
        "regular_price": 1578.99,
        "sale_start": "2022-07-24 02:00:00",
        "sale_end": "2022-08-01 00:00:00",
        "url": "https://lenta.com/product/kalmar-kolca-solenosushenye-ves-rossiya-1kg-507591/"
    },
    {
        "title": "Сардина Иваси холодного копчения, неразделанная, весовая",
        "sale_percent": 15,
        "card_price": 223.69,
        "regular_price": 263.19,
        "sale_start": "2022-07-24 02:00:00",
        "sale_end": "2022-11-04 02:00:00",
        "url": "https://lenta.com/product/sardina-ivasi-nerazdelannaya-hk-ves-rossiya-1kg-492543/"
    },
    {
        "title": "Рулет горячего копчения из горбуши и скумбрии, весовой",
        "sale_percent": 28,
        "card_price": 649.99,
        "regular_price": 905.29,
        "sale_start": "2022-07-24 02:00:00",
        "sale_end": "2022-08-01 02:00:00",
        "url": "https://lenta.com/product/rulet-gorbushaskumbriya-gk-ves-rossiya-104734/"
    },
    {
        "title": "Минтай сушеный, филе шинкованное, весовой",
        "sale_percent": 20,
        "card_price": 1099.99,
        "regular_price": 1367.39,
        "sale_start": "2022-07-24 02:00:00",
        "sale_end": "2022-08-01 00:00:00",
        "url": "https://lenta.com/product/mintajj-file-sushenoe-shinkovannoe-ves-rossiya-206858/"
    },
    {
        "title": "Кета холодного копчения, балык (спинка), весовая",
        "sale_percent": 15,
        "card_price": 1070.89,
        "regular_price": 1259.89,
        "sale_start": "2022-07-24 02:00:00",
        "sale_end": "2022-11-04 02:00:00",
        "url": "https://lenta.com/product/keta-balyk-spinka-hk-ves-rossiya-104492/"
    },
    {
        "title": "Кета холодного копчения РЫБНЫЙ ХИТ балык (спинка), весовая",
        "sale_percent": 15,
        "card_price": 1073.69,
        "regular_price": 1263.19,
        "sale_start": "2022-07-24 02:00:00",
        "sale_end": "2022-11-04 02:00:00",
        "url": "https://lenta.com/product/keta-rybnyjj-hit-balyk-spinka-hk-ves-rossiya-599377/"
    },
    {
        "title": "Камбала вяленая, весовая",
        "sale_percent": 15,
        "card_price": 590.49,
        "regular_price": 694.79,
        "sale_start": "2022-07-24 02:00:00",
        "sale_end": "2022-11-04 02:00:00",
        "url": "https://lenta.com/product/kambala-vyalenaya-ves-rossiya-104718/"
    },
    {
        "title": "Терпуг горячего копчения, потрошеный с головой, весовой",
        "sale_percent": 15,
        "card_price": 411.59,
        "regular_price": 484.29,
        "sale_start": "2022-07-24 02:00:00",
        "sale_end": "2022-11-04 02:00:00",
        "url": "https://lenta.com/product/terpug-potr-sg-gk-ves-rossiya-517554/"
    },
    {
        "title": "Сельдь слабосоленая крупная 200–300г, весовая",
        "sale_percent": 15,
        "card_price": 232.59,
        "regular_price": 273.69,
        "sale_start": "2022-07-24 02:00:00",
        "sale_end": "2022-11-04 02:00:00",
        "url": "https://lenta.com/product/seld-krupnaya-300-ss-ves-rossiya-1kg-104736/"
    },
    {
        "title": "Сельдь холодного копчения, филе, весовая",
        "sale_percent": 15,
        "card_price": 304.19,
        "regular_price": 357.89,
        "sale_start": "2022-07-24 02:00:00",
        "sale_end": "2022-11-04 02:00:00",
        "url": "https://lenta.com/product/seld-file-hk-ves-rossiya-117247/"
    },
    {
        "title": "Сельдь Тихоокеанская слабосоленая, весовая",
        "sale_percent": 15,
        "card_price": 160.99,
        "regular_price": 189.49,
        "sale_start": "2022-07-24 02:00:00",
        "sale_end": "2022-11-04 02:00:00",
        "url": "https://lenta.com/product/seld-ss-to-ves-rossiya-076321/"
    },
    {
        "title": "Лещ вяленый, весовой",
        "sale_percent": 15,
        "card_price": 223.69,
        "regular_price": 263.19,
        "sale_start": "2022-07-24 02:00:00",
        "sale_end": "2022-11-04 02:00:00",
        "url": "https://lenta.com/product/leshch-vyalenyjj-ves-rossiya-092840/"
    },
    {
        "title": "Сельдь холодного копчения крупная, весовая",
        "sale_percent": 15,
        "card_price": 265.69,
        "regular_price": 312.69,
        "sale_start": "2022-07-24 02:00:00",
        "sale_end": "2022-11-04 02:00:00",
        "url": "https://lenta.com/product/seld-krupnaya-hk-ves-rossiya-141389/"
    },
    {
        "title": "Путассу холодного копчения, неразделанная, весовая",
        "sale_percent": 15,
        "card_price": 277.39,
        "regular_price": 326.39,
        "sale_start": "2022-07-24 02:00:00",
        "sale_end": "2022-11-04 02:00:00",
        "url": "https://lenta.com/product/putassu-nr-hk-ves-rossiya-514812/"
    },
    {
        "title": "Минтай горячего копчения, весовой",
        "sale_percent": 15,
        "card_price": 314.79,
        "regular_price": 370.39,
        "sale_start": "2022-07-24 02:00:00",
        "sale_end": "2022-11-04 02:00:00",
        "url": "https://lenta.com/product/mintajj-gk-ves-rossiya-512539/"
    },
    {
        "title": "Мойва пряного посола неразделанная, весовая",
        "sale_percent": 15,
        "card_price": 357.89,
        "regular_price": 421.09,
        "sale_start": "2022-07-24 02:00:00",
        "sale_end": "2022-11-04 02:00:00",
        "url": "https://lenta.com/product/mojjva-prochie-tovary-pryanogo-posola-nr-ves-rossiya-636446/"
    },
    {
        "title": "Скумбрия горячего копчения, весовая",
        "sale_percent": 15,
        "card_price": 402.59,
        "regular_price": 473.69,
        "sale_start": "2022-07-24 02:00:00",
        "sale_end": "2022-11-04 02:00:00",
        "url": "https://lenta.com/product/skumbriya-gk-sp-ves-rossiya-258105/"
    },
    {
        "title": "Камбала холодного копчения, потрошеная с головой, весовая",
        "sale_percent": 15,
        "card_price": 402.59,
        "regular_price": 473.69,
        "sale_start": "2022-07-24 02:00:00",
        "sale_end": "2022-11-04 02:00:00",
        "url": "https://lenta.com/product/kambala-prochie-tovary-sg-hk-potr-ves-rossiya-610461/"
    },
    {
        "title": "Язь горячего копчения, пласт, весовой",
        "sale_percent": 15,
        "card_price": 428.59,
        "regular_price": 504.29,
        "sale_start": "2022-07-24 02:00:00",
        "sale_end": "2022-11-04 02:00:00",
        "url": "https://lenta.com/product/yaz-plast-gk-ves-rossiya-516891/"
    },
    {
        "title": "Судак холодного копчения, калтычок, весовой",
        "sale_percent": 15,
        "card_price": 483.19,
        "regular_price": 568.49,
        "sale_start": "2022-07-24 02:00:00",
        "sale_end": "2022-11-04 02:00:00",
        "url": "https://lenta.com/product/sudak-kaltychok-hk-ves-rossiya-1kg-510692/"
    }
]