[
    {
        "title": "Жидкое крем-мыло для интимной гигиены EVO, 200мл",
        "sale_percent": 15,
        "card_price": 106.39,
        "regular_price": 125.29,
        "sale_start": "2022-07-24 02:00:00",
        "sale_end": "2022-10-05 02:00:00",
        "url": "https://lenta.com/product/zhidkoe-kremmylo-evo-dintim-gigieny-rossiya-200ml-309964/"
    },
    {
        "title": "Средство для интимной гигиены LACTACYD Classic, 200мл",
        "sale_percent": 15,
        "card_price": 321.19,
        "regular_price": 377.89,
        "sale_start": "2022-07-24 02:00:00",
        "sale_end": "2022-10-05 02:00:00",
        "url": "https://lenta.com/product/sredstvo-lactacyd-dintimnojj-gigieny-franciya-200ml-300078/"
    },
    {
        "title": "Тампоны HELEN HARPER Normal безаппликаторные, 16шт",
        "sale_percent": 15,
        "card_price": 196.79,
        "regular_price": 231.59,
        "sale_start": "2022-07-24 02:00:00",
        "sale_end": "2022-10-05 02:00:00",
        "url": "https://lenta.com/product/tampony-prochie-tovary-normal-bezapplikatornye-germaniya-16sht-630178/"
    },
    {
        "title": "Прокладки гигиенические BELLA Nova Comfort, 10шт",
        "sale_percent": 15,
        "card_price": 80.49,
        "regular_price": 94.79,
        "sale_start": "2022-07-24 02:00:00",
        "sale_end": "2022-10-05 02:00:00",
        "url": "https://lenta.com/product/prokladki-bella-nova-comfort-gigien-rossiya-10sht-354235/"
    },
    {
        "title": "Тампоны HELEN HARPER Super Plus безаппликаторные, 16шт",
        "sale_percent": 15,
        "card_price": 214.69,
        "regular_price": 252.69,
        "sale_start": "2022-07-29 02:00:00",
        "sale_end": "2022-11-06 02:00:00",
        "url": "https://lenta.com/product/tampony-prochie-tovary-super-plus-bezapplikatornye-germaniya-16sht-630132/"
    },
    {
        "title": "Жидкое мыло для интимной гигиены EVO для чувствительной кожи, 200мл",
        "sale_percent": 15,
        "card_price": 106.39,
        "regular_price": 125.29,
        "sale_start": "2022-07-24 02:00:00",
        "sale_end": "2022-10-05 02:00:00",
        "url": "https://lenta.com/product/zhidkoe-mylo-evo-dintim-gigieny-dchuvstvit-kozhi-rossiya-200ml-310418/"
    },
    {
        "title": "Прокладки гигиенические BELLA Ultra Relax Deo супертонкие, впитывающие, 10шт",
        "sale_percent": 15,
        "card_price": 107.39,
        "regular_price": 126.39,
        "sale_start": "2022-07-24 02:00:00",
        "sale_end": "2022-10-05 02:00:00",
        "url": "https://lenta.com/product/prokladki-bella-for-teens-ultra-relax-deo-supertonkie-gigien-vpityvayushchie-polsha-10sht-193629/"
    },
    {
        "title": "Прокладки BELLA Nova Maxi, 10шт",
        "sale_percent": 15,
        "card_price": 84.89,
        "regular_price": 99.89,
        "sale_start": "2022-07-24 02:00:00",
        "sale_end": "2022-10-05 02:00:00",
        "url": "https://lenta.com/product/prokladki-bella-nova-maxi-softiplait-air-rossiya-10sht-324124/"
    },
    {
        "title": "Прокладки гигиенические BELLA Ultra Sensitive супертонкие, впитывающие, 10шт",
        "sale_percent": 15,
        "card_price": 107.39,
        "regular_price": 126.39,
        "sale_start": "2022-07-24 02:00:00",
        "sale_end": "2022-10-05 02:00:00",
        "url": "https://lenta.com/product/prokladki-bella-for-teens-ultra-sensitive-supertonkie-gigien-vpityvayushchie-polsha-10sht-193633/"
    },
    {
        "title": "Прокладки ежедневные OLA! Daily экономичная упаковка, 60шт",
        "sale_percent": 15,
        "card_price": 125.09,
        "regular_price": 147.29,
        "sale_start": "2022-07-24 02:00:00",
        "sale_end": "2022-10-05 02:00:00",
        "url": "https://lenta.com/product/prokladki-ola-daily-ekonomupak-rossiya-60sht-266437/"
    },
    {
        "title": "Прокладки ежедневные BELLA Panty Soft Classic, 60шт",
        "sale_percent": 15,
        "card_price": 139.49,
        "regular_price": 164.19,
        "sale_start": "2022-07-24 02:00:00",
        "sale_end": "2022-10-05 02:00:00",
        "url": "https://lenta.com/product/prokladki-bella-panty-soft-classic-ezhedn-rossiya-60sht-456556/"
    },
    {
        "title": "Прокладки LAURIER Super Absorbent ночные с крылышками, 7шт",
        "sale_percent": 15,
        "card_price": 411.59,
        "regular_price": 484.29,
        "sale_start": "2022-07-26 02:00:00",
        "sale_end": "2022-10-05 02:00:00",
        "url": "https://lenta.com/product/prokladki-laurier-super-absorbent-nochnye-gigienicheskie-s-krylyshkami-yaponiya-7sht-635019/"
    },
    {
        "title": "Жидкое мыло для интимной гигиены КРАСНАЯ ЛИНИЯ с экстрактом хлопка, 250мл",
        "sale_percent": 15,
        "card_price": 146.69,
        "regular_price": 172.69,
        "sale_start": "2022-07-29 02:00:00",
        "sale_end": "2022-11-06 02:00:00",
        "url": "https://lenta.com/product/zhidkoe-mylo-krasnaya-liniya-s-ekstraktom-hlopka-dintimgigieny-rossiya-250ml-259052/"
    },
    {
        "title": "Прокладки ночные KOTEX Natural, 12шт",
        "sale_percent": 27,
        "card_price": 249.99,
        "regular_price": 343.19,
        "sale_start": "2022-07-24 02:00:00",
        "sale_end": "2022-08-01 00:00:00",
        "url": "https://lenta.com/product/568309-chehiya-568309/"
    },
    {
        "title": "Прокладки гигиенические KOTEX Ultra Normal, 10шт",
        "sale_percent": 30,
        "card_price": 139.99,
        "regular_price": 198.99,
        "sale_start": "2022-07-24 02:00:00",
        "sale_end": "2022-08-01 00:00:00",
        "url": "https://lenta.com/product/prokladki-kotex-ultra-setch-normal-gig-rossiya-10sht-241026/"
    },
    {
        "title": "Прокладки KOTEX Natural Супер, 14шт",
        "sale_percent": 27,
        "card_price": 249.99,
        "regular_price": 343.19,
        "sale_start": "2022-07-24 02:00:00",
        "sale_end": "2022-08-01 00:00:00",
        "url": "https://lenta.com/product/prokladki-kotex-organik-super-chehiya-14sht-549614/"
    },
    {
        "title": "Прокладки MONTY Ultra Thin Normal Plus, 10шт",
        "sale_percent": 15,
        "card_price": 147.59,
        "regular_price": 173.69,
        "sale_start": "2022-07-24 02:00:00",
        "sale_end": "2022-08-03 00:00:00",
        "url": "https://lenta.com/product/prokladki-monty-ultra-thin-normal-plus-kitajj-10sht-637343/"
    },
    {
        "title": "Прокладки гигиенические JENNA Ultra Soft Normal, 20шт",
        "sale_percent": 15,
        "card_price": 186.09,
        "regular_price": 218.99,
        "sale_start": "2022-07-24 02:00:00",
        "sale_end": "2022-10-05 02:00:00",
        "url": "https://lenta.com/product/prokladki-jenna-ultra-soft-normal-gigien-rossiya-20sht-570900/"
    },
    {
        "title": "Тампоны HELEN HARPER Super безаппликаторные, 16шт",
        "sale_percent": 15,
        "card_price": 205.79,
        "regular_price": 242.19,
        "sale_start": "2022-07-24 02:00:00",
        "sale_end": "2022-10-05 02:00:00",
        "url": "https://lenta.com/product/tampony-prochie-tovary-super-bezapplikatornye-germaniya-16sht-629903/"
    },
    {
        "title": "Прокладки ежедневные NATURELLA Ромашка Лайт Мультиформ, 52шт",
        "sale_percent": 15,
        "card_price": 267.49,
        "regular_price": 314.79,
        "sale_start": "2022-07-24 02:00:00",
        "sale_end": "2022-10-05 02:00:00",
        "url": "https://lenta.com/product/prokladki-naturella-romashka-lajjt-multiform-na-kazhdyjj-den-germaniya-52sht-574180/"
    },
    {
        "title": "Прокладки ежедневные O2 Ultra thin, 20шт",
        "sale_percent": 15,
        "card_price": 125.19,
        "regular_price": 147.39,
        "sale_start": "2022-07-26 02:00:00",
        "sale_end": "2022-10-05 02:00:00",
        "url": "https://lenta.com/product/prokladki-prochie-tovary-ultra-thin-ezhednevnye-kitajj-20sht-627291/"
    },
    {
        "title": "Прокладки ночные LAURIER F 30см тонкие, с крылышками, 10шт",
        "sale_percent": 14,
        "card_price": 465.19,
        "regular_price": 542.19,
        "sale_start": "2022-07-26 02:00:00",
        "sale_end": "2022-10-05 02:00:00",
        "url": "https://lenta.com/product/prokladki-laurier-f-nochnye-tonkie-s-krylyshkami-30sm-yaponiya-10sht-517974/"
    },
    {
        "title": "Салфетки влажные для интимной гигиены Я САМАЯ c соком алоэ, 15шт",
        "sale_percent": 15,
        "card_price": 71.59,
        "regular_price": 84.29,
        "sale_start": "2022-07-26 02:00:00",
        "sale_end": "2022-10-05 02:00:00",
        "url": "https://lenta.com/product/salfetki-ya-samaya-aloe-dintimnojj-gigieny-vlazh-rossiya-15sht-220503/"
    },
    {
        "title": "Прокладки KOTEX Natural Super, 7шт",
        "sale_percent": 25,
        "card_price": 139.89,
        "regular_price": 185.29,
        "sale_start": "2022-07-24 02:00:00",
        "sale_end": "2022-08-01 00:00:00",
        "url": "https://lenta.com/product/prokladki-prochie-tovary-natural-super-chehiya-7sht-626703/"
    }
]